<?xml version="1.0" encoding="UTF-8"?>
<schemalist gettext-domain="drill">
	<schema id="io.github.johnpetersa.Drill" path="/io/github/johnpetersa/Drill/">
		<key name="window-width" type="i">
			<default>1120</default>
			<summary>Window width</summary>
			<description>The last saved main window width.</description>
		</key>
		<key name="window-height" type="i">
			<default>720</default>
			<summary>Window height</summary>
			<description>The last saved main window height.</description>
		</key>
		<key name="window-maximized" type="b">
			<default>false</default>
			<summary>Window maximized state</summary>
			<description>Whether the main window was maximized when the application last closed.</description>
		</key>
		<key name="preferences-width" type="i">
			<default>720</default>
			<summary>Preferences width</summary>
			<description>The last saved preferences dialog content width.</description>
		</key>
		<key name="preferences-height" type="i">
			<default>520</default>
			<summary>Preferences height</summary>
			<description>The last saved preferences dialog content height.</description>
		</key>
		<key name="signature-database-source" type="s">
			<default>'builtin'</default>
			<summary>Signature database source</summary>
			<description>Whether Drill uses the built-in signature database or a local JSON database selected by the user.</description>
		</key>
		<key name="signature-database-path" type="s">
			<default>''</default>
			<summary>Local signature database path</summary>
			<description>The path to the user-selected local signature database JSON file.</description>
		</key>
	</schema>
</schemalist>
